setup_server_whl.py
mess_test_server.egg-info/PKG-INFO
mess_test_server.egg-info/SOURCES.txt
mess_test_server.egg-info/dependency_links.txt
mess_test_server.egg-info/requires.txt
mess_test_server.egg-info/top_level.txt
server/__init__.py
server/server.py
server/common/__init__.py
server/common/decors.py
server/common/descriptors.py
server/common/errors.py
server/common/metaclass.py
server/common/utils.py
server/common/variables.py
server/log/__init__.py
server/log/config_client_log.py
server/log/config_server_log.py
server/server/__init__.py
server/server/add_user.py
server/server/config_window.py
server/server/core.py
server/server/database.py
server/server/main_window.py
server/server/remove_user.py
server/server/stat_window.py
server/unit_tests/__init__.py
server/unit_tests/test_client.py
server/unit_tests/test_server.py
server/unit_tests/test_utils.py