Metadata-Version: 2.1
Name: mess-test-server
Version: 0.0.1
Summary: mess_test_server
Author: Aleksey Ovchinnikov
Author-email: denetor89@yandex.ru
License: UNKNOWN
Platform: UNKNOWN
